LICENSE
MANIFEST.in
README.md
setup.py
docs/conf.py
docs/generate-examples-geoareas.py
docs/generate-examples-maps.py
docs/print-magics-objects.py
docs/examples/magpye.py
docs/gallery/geoareas/africa.py
docs/gallery/geoareas/antarctic.py
docs/gallery/geoareas/arctic.py
docs/gallery/geoareas/australasia.py
docs/gallery/geoareas/central_america.py
docs/gallery/geoareas/central_europe.py
docs/gallery/geoareas/east_tropic.py
docs/gallery/geoareas/eastern_asia.py
docs/gallery/geoareas/eurasia.py
docs/gallery/geoareas/europe.py
docs/gallery/geoareas/global.py
docs/gallery/geoareas/middle_east_and_india.py
docs/gallery/geoareas/north_america.py
docs/gallery/geoareas/north_atlantic.py
docs/gallery/geoareas/north_east_europe.py
docs/gallery/geoareas/north_pole.py
docs/gallery/geoareas/north_west_europe.py
docs/gallery/geoareas/northern_africa.py
docs/gallery/geoareas/pacific.py
docs/gallery/geoareas/south_america.py
docs/gallery/geoareas/south_atlantic_and_indian_ocean.py
docs/gallery/geoareas/south_east_asia_and_indonesia.py
docs/gallery/geoareas/south_east_europe.py
docs/gallery/geoareas/south_pole.py
docs/gallery/geoareas/south_west_europe.py
docs/gallery/geoareas/southern_africa.py
docs/gallery/geoareas/southern_asia.py
docs/gallery/geoareas/west_tropic.py
docs/gallery/geoareas/western_asia.py
docs/geoareas/geoareas.py
magpye/__init__.py
magpye/_helpers.py
magpye/action.py
magpye/config.py
magpye/geomap.py
magpye/macro.py
magpye/quick_plot.py
magpye/styles.py
magpye.egg-info/PKG-INFO
magpye.egg-info/SOURCES.txt
magpye.egg-info/dependency_links.txt
magpye.egg-info/requires.txt
magpye.egg-info/top_level.txt
magpye.egg-info/zip-safe
magpye/data/__init__.py
magpye/data/_data.py
magpye/data/ecdata.py
magpye/data/grib.py
magpye/data/netcdf.py
magpye/data/temporary.py
magpye/static/styles/contour_lines/black_i4.yaml
magpye/static/styles/contour_lines/black_i5.yaml
magpye/static/styles/contour_lines/black_i5_LH.yaml
magpye/static/styles/contour_lines/black_i5_label.yaml
magpye/static/styles/contour_lines/blue_i5.yaml
magpye/static/styles/contour_lines/magenta_i2.yaml
magpye/static/styles/contour_lines/red_dash_i2.yaml
